data_augmentation_app/__init__.py
data_augmentation_app/augmentation_core.py
data_augmentation_app/cli.py
data_augmentation_app/data_augmentation_main.py
data_augmentation_app/layers_personalizadas.py
data_augmentation_app-0.1.4.dist-info/METADATA
data_augmentation_app-0.1.4.dist-info/WHEEL
data_augmentation_app-0.1.4.dist-info/entry_points.txt
data_augmentation_app-0.1.4.dist-info/top_level.txt
data_augmentation_app-0.1.4.dist-info/RECORD
