Metadata-Version: 2.4
Name: data-augmentation-app
Version: 0.1.4
Summary: GUI & CLI for image data augmentation with TensorFlow/Keras
Author-email: Javier García Viadero <javiergarciaviadero13@gmail.com>
Requires-Python: >=3.9
Requires-Dist: tensorflow>=2.15
Requires-Dist: pyqt5
Requires-Dist: numpy
Requires-Dist: pillow
